[
  {
    "creator": "Holly Evans,Maanya Sachdeva,Tom Murray and Kevin E G Perry",
    "date": "2023-11-30T23:27:42+00:00",
    "title": "Shane MacGowan dead - latest: Pogues singer known for Fairytale of New York dies as tributes paid",
    "link": "https://www.independent.co.uk/arts-entertainment/music/news/shane-macgowan-pogues-death-singer-b2456118.html",
    "pubDate": "Thu, 30 Nov 2023 23:27:42 GMT",
    "dc:creator": "Holly Evans,Maanya Sachdeva,Tom Murray and Kevin E G Perry",
    "dc:date": "2023-11-30T23:27:42+00:00",
    "content": "<p>His death comes one week after he was discharged from hospital  </p>",
    "contentSnippet": "His death comes one week after he was discharged from hospital",
    "guid": "b2456118",
    "categories": [
      "News",
      "Music",
      "Culture"
    ],
    "isoDate": "2023-11-30T23:27:42.000Z"
  },
  {
    "creator": "Tom Krisher",
    "date": "2023-11-30T23:26:33+00:00",
    "title": "Tesla delivers 13 stainless steel Cybertruck pickups as it tries to work out production problems",
    "link": "https://www.independent.co.uk/news/tesla-cybertruck-pickup-elon-musk-b2456522.html",
    "pubDate": "Thu, 30 Nov 2023 23:26:33 GMT",
    "dc:creator": "Tom Krisher",
    "dc:date": "2023-11-30T23:26:33+00:00",
    "content": "With manufacturing kinks still to be worked out, Tesla has delivered the first dozen or so of its futuristic Cybertruck pickups to customers",
    "contentSnippet": "With manufacturing kinks still to be worked out, Tesla has delivered the first dozen or so of its futuristic Cybertruck pickups to customers",
    "guid": "b2456522",
    "isoDate": "2023-11-30T23:26:33.000Z"
  },
  {
    "creator": "Rhys Jones",
    "date": "2023-11-30T23:23:18+00:00",
    "title": "Simon Calder delivers verdict on rail disruption this winter",
    "link": "https://www.independent.co.uk/tv/news/rail-strikes-news-december-simon-calder-b2456521.html",
    "pubDate": "Thu, 30 Nov 2023 23:23:18 GMT",
    "dc:creator": "Rhys Jones",
    "dc:date": "2023-11-30T23:23:18+00:00",
    "content": "<p>Watch The Independent’s <a href=\"/topic/travel\">Travel</a> correspondent, <a href=\"/topic/simon-calder\">Simon Calder</a>, deliver his verdict on the train strikes coming this winter and how they might affect you.</p>",
    "contentSnippet": "Watch The Independent’s Travel correspondent, Simon Calder, deliver his verdict on the train strikes coming this winter and how they might affect you.",
    "guid": "b2456521",
    "categories": [
      "News",
      "Indy TV"
    ],
    "isoDate": "2023-11-30T23:23:18.000Z"
  },
  {
    "creator": "Holly Evans",
    "date": "2023-11-30T23:21:15+00:00",
    "title": "Omid Scobie refuses to apologise over Endgame ‘error’ as Dutch translator breaks silence - latest",
    "link": "https://www.independent.co.uk/life-style/royal-family/royals-dutch-endgame-omid-scobie-piers-morgan-b2455926.html",
    "pubDate": "Thu, 30 Nov 2023 23:21:15 GMT",
    "dc:creator": "Holly Evans",
    "dc:date": "2023-11-30T23:21:15+00:00",
    "content": "<p>‘It’s not for me to apologise,’ says author Omid Scobie </p>",
    "contentSnippet": "‘It’s not for me to apologise,’ says author Omid Scobie",
    "guid": "b2455926",
    "categories": [
      "Royal Family",
      "Lifestyle"
    ],
    "isoDate": "2023-11-30T23:21:15.000Z"
  },
  {
    "creator": "Holly Patrick",
    "date": "2023-11-30T23:14:42+00:00",
    "title": "Unusual ‘pancake’ ice phenomenon covers lake in Wisconsin as temperatures drop",
    "link": "https://www.independent.co.uk/tv/news/weather-wisconsin-ice-lake-pancake-b2456268.html",
    "pubDate": "Thu, 30 Nov 2023 23:14:42 GMT",
    "dc:creator": "Holly Patrick",
    "dc:date": "2023-11-30T23:14:42+00:00",
    "content": "<p>Unusual <a href=\"https://www.independent.co.uk/tv/news/lake-effect-snow-buffalo-new-york-b2455658.html\">ice</a> \"pancakes\" formed on top of <a href=\"/topic/lake-superior\">Lake Superior</a> in northern <a href=\"/topic/wisconsin\">Wisconsin</a> on Tuesday, 28 November, video shows.</p>",
    "contentSnippet": "Unusual ice \"pancakes\" formed on top of Lake Superior in northern Wisconsin on Tuesday, 28 November, video shows.",
    "guid": "b2456268",
    "categories": [
      "News",
      "Indy TV"
    ],
    "isoDate": "2023-11-30T23:14:42.000Z"
  },
  {
    "creator": "Bevan Hurley",
    "date": "2023-11-30T23:14:37+00:00",
    "title": "Florida GOP chair accused of rape by woman he and wife were reportedly having affair with",
    "link": "https://www.the-independent.com/news/world/americas/crime/christian-ziegler-florida-moms-for-liberty-b2456473.html",
    "pubDate": "Thu, 30 Nov 2023 23:14:37 GMT",
    "dc:creator": "Bevan Hurley",
    "dc:date": "2023-11-30T23:14:37+00:00",
    "content": "<p>‘As leaders in the Florida GOP and Moms for Liberty, the Zieglers have made a habit out of attacking anything they perceive as going against ‘family values’,’ Florida Democratic Party chair Nikki Fried says </p>",
    "contentSnippet": "‘As leaders in the Florida GOP and Moms for Liberty, the Zieglers have made a habit out of attacking anything they perceive as going against ‘family values’,’ Florida Democratic Party chair Nikki Fried says",
    "guid": "b2456473",
    "categories": [
      "US Crime News",
      "Americas",
      "World"
    ],
    "isoDate": "2023-11-30T23:14:37.000Z"
  },
  {
    "creator": "John Bowden",
    "date": "2023-11-30T23:09:51+00:00",
    "title": "Arizona GOP officials charged with refusing to certify 2022 election results",
    "link": "https://www.the-independent.com/news/world/americas/us-politics/gop-arizona-election-fraud-charges-b2456516.html",
    "pubDate": "Thu, 30 Nov 2023 23:09:51 GMT",
    "dc:creator": "John Bowden",
    "dc:date": "2023-11-30T23:09:51+00:00",
    "content": "<p>Two Republicans face twin felony counts stemming from 2022 dispute </p>",
    "contentSnippet": "Two Republicans face twin felony counts stemming from 2022 dispute",
    "guid": "b2456516",
    "categories": [
      "US politics",
      "Americas",
      "World"
    ],
    "isoDate": "2023-11-30T23:09:51.000Z"
  },
  {
    "creator": "Rhys Jones",
    "date": "2023-11-30T23:08:49+00:00",
    "title": "Pro-Palestine students protest at Canada school board meeting forcing trustees to walk out",
    "link": "https://www.independent.co.uk/tv/news/propalestine-students-protest-canada-b2456517.html",
    "pubDate": "Thu, 30 Nov 2023 23:08:49 GMT",
    "dc:creator": "Rhys Jones",
    "dc:date": "2023-11-30T23:08:49+00:00",
    "content": "<p>Pro-Palestinian <a href=\"/topic/demonstrators\">demonstrators</a> broke up a school board meeting in <a href=\"/topic/ontario\">Ontario</a> on Wednesday 29 November. </p>",
    "contentSnippet": "Pro-Palestinian demonstrators broke up a school board meeting in Ontario on Wednesday 29 November.",
    "guid": "b2456517",
    "categories": [
      "News",
      "Indy TV"
    ],
    "isoDate": "2023-11-30T23:08:49.000Z"
  },
  {
    "creator": "Graeme Massie and Michelle Del Rey",
    "date": "2023-11-30T23:07:45+00:00",
    "title": "Jonathan Majors jury selected in assault trial: Live",
    "link": "https://www.independent.co.uk/news/world/americas/jonathan-majors-trial-domestic-violence-meagan-good-b2455966.html",
    "pubDate": "Thu, 30 Nov 2023 23:07:45 GMT",
    "dc:creator": "Graeme Massie and Michelle Del Rey",
    "dc:date": "2023-11-30T23:07:45+00:00",
    "content": "<p>Marvel actor’s girlfriend Meagan Good is standing by him as trial begins</p>",
    "contentSnippet": "Marvel actor’s girlfriend Meagan Good is standing by him as trial begins",
    "guid": "b2455966",
    "categories": [
      "Americas",
      "World"
    ],
    "isoDate": "2023-11-30T23:07:45.000Z"
  },
  {
    "creator": "Andrea Blanco and Ariana Baio",
    "date": "2023-11-30T23:07:00+00:00",
    "title": "Henry Kissinger: A life in pictures",
    "link": "https://www.independent.co.uk/news/world/americas/henry-kissinger-death-pictures-life-b2456202.html",
    "pubDate": "Thu, 30 Nov 2023 23:07:00 GMT",
    "dc:creator": "Andrea Blanco and Ariana Baio",
    "dc:date": "2023-11-30T23:07:00+00:00",
    "content": "<p>The death of Kissinger, hailed by many as the architect of American foreign policy, was announced on Wednesday. Andrea Blanco and Ariana Baio report  </p>",
    "contentSnippet": "The death of Kissinger, hailed by many as the architect of American foreign policy, was announced on Wednesday. Andrea Blanco and Ariana Baio report",
    "guid": "b2456202",
    "categories": [
      "Americas",
      "World"
    ],
    "isoDate": "2023-11-30T23:07:00.000Z"
  },
  {
    "creator": "Isobel Lewis",
    "date": "2023-11-30T23:03:37+00:00",
    "title": "Sam Thompson admits fears about ADHD and parenthood on I’m a Celebrity",
    "link": "https://www.independent.co.uk/arts-entertainment/tv/news/sam-thompson-adhd-zara-mcdermott-b2456504.html",
    "pubDate": "Thu, 30 Nov 2023 23:03:37 GMT",
    "dc:creator": "Isobel Lewis",
    "dc:date": "2023-11-30T23:03:37+00:00",
    "content": "<p>‘Made in Chelsea’ star was diagnosed with behavioural disorder aged 30 </p>",
    "contentSnippet": "‘Made in Chelsea’ star was diagnosed with behavioural disorder aged 30",
    "guid": "b2456504",
    "categories": [
      "News",
      "TV &amp; Radio",
      "Culture"
    ],
    "isoDate": "2023-11-30T23:03:37.000Z"
  },
  {
    "creator": "Roisin O'Connor",
    "date": "2023-11-30T23:03:00+00:00",
    "title": "Renaissance: A Film by Beyoncé: Concert film shows a level of perfectionism beyond any other artist",
    "link": "https://www.independent.co.uk/arts-entertainment/music/reviews/beyonce-renaissance-film-review-tour-setlist-b2456225.html",
    "pubDate": "Thu, 30 Nov 2023 23:03:00 GMT",
    "dc:creator": "Roisin O'Connor",
    "dc:date": "2023-11-30T23:03:00+00:00",
    "content": "<p>Everything appears flawless, but the US pop titan offers a behind-the-scenes look at just how much work that takes</p>",
    "contentSnippet": "Everything appears flawless, but the US pop titan offers a behind-the-scenes look at just how much work that takes",
    "guid": "b2456225",
    "categories": [
      "Reviews",
      "Music",
      "Culture"
    ],
    "isoDate": "2023-11-30T23:03:00.000Z"
  },
  {
    "creator": "Nick Mashiter",
    "date": "2023-11-30T23:01:48+00:00",
    "title": "Unai Emery eager to top group after Aston Villa reach ECL knockout stages",
    "link": "https://www.independent.co.uk/sport/football/aston-villa-legia-warsaw-unai-emery-europa-conference-league-villa-b2456519.html",
    "pubDate": "Thu, 30 Nov 2023 23:01:48 GMT",
    "dc:creator": "Nick Mashiter",
    "dc:date": "2023-11-30T23:01:48+00:00",
    "content": "Villa moved top of Group E after victory over Legia Warsaw.",
    "contentSnippet": "Villa moved top of Group E after victory over Legia Warsaw.",
    "guid": "b2456519",
    "categories": [
      "Football",
      "Sport"
    ],
    "isoDate": "2023-11-30T23:01:48.000Z"
  },
  {
    "creator": "Oliver O'Connell and Alex Woodward",
    "date": "2023-11-30T23:01:18+00:00",
    "title": "Trump hits out at judge’s wife as fraud trial gag order reinstated: Live",
    "link": "https://www.independent.co.uk/news/world/americas/donald-trump-news-today-sebastian-stan-latest-b2455990.html",
    "pubDate": "Thu, 30 Nov 2023 23:01:18 GMT",
    "dc:creator": "Oliver O'Connell and Alex Woodward",
    "dc:date": "2023-11-30T23:01:18+00:00",
    "content": "<p>Justice Arthur Engoron and his principal law clerk were subjected to ‘hundreds of threats’ after former president’s Truth Social posts, now Trump lashes out at  judge’s wife</p>",
    "contentSnippet": "Justice Arthur Engoron and his principal law clerk were subjected to ‘hundreds of threats’ after former president’s Truth Social posts, now Trump lashes out at  judge’s wife",
    "guid": "b2455990",
    "categories": [
      "Americas",
      "World"
    ],
    "isoDate": "2023-11-30T23:01:18.000Z"
  },
  {
    "creator": "Andy Sims",
    "date": "2023-11-30T23:00:13+00:00",
    "title": "Tomas Soucek snatches late winner for West Ham in otherwise uneventful clash in Serbia",
    "link": "https://www.independent.co.uk/sport/football/west-ham-tomas-soucek-serbia-said-benrahma-david-moyes-b2456424.html",
    "pubDate": "Thu, 30 Nov 2023 23:00:13 GMT",
    "dc:creator": "Andy Sims",
    "dc:date": "2023-11-30T23:00:13+00:00",
    "content": "<p>The Czech midfielder has now scored in his last five matches for club and country</p>",
    "contentSnippet": "The Czech midfielder has now scored in his last five matches for club and country",
    "guid": "b2456424",
    "categories": [
      "Football",
      "Sport"
    ],
    "isoDate": "2023-11-30T23:00:13.000Z"
  },
  {
    "creator": "Graeme Massie,Maroosha Muzaffar,Rachel Sharp and Ariana Baio",
    "date": "2023-11-30T22:59:20+00:00",
    "title": "Biden says he ‘often strongly’ disagreed with Kissinger after diplomat’s death: Latest",
    "link": "https://www.independent.co.uk/news/world/americas/henry-kissinger-dead-age-cause-of-death-controversy-b2455941.html",
    "pubDate": "Thu, 30 Nov 2023 22:59:20 GMT",
    "dc:creator": "Graeme Massie,Maroosha Muzaffar,Rachel Sharp and Ariana Baio",
    "dc:date": "2023-11-30T22:59:20+00:00",
    "content": "<p>Henry Kissinger leaves behind a complex legacy, remembered as a master of global politics by some and an alleged war criminal by others</p>",
    "contentSnippet": "Henry Kissinger leaves behind a complex legacy, remembered as a master of global politics by some and an alleged war criminal by others",
    "guid": "b2455941",
    "categories": [
      "Americas",
      "World"
    ],
    "isoDate": "2023-11-30T22:59:20.000Z"
  },
  {
    "creator": "Ed Elliot",
    "date": "2023-11-30T22:58:24+00:00",
    "title": "Joao Pedro penalty sends Brighton through to Europa League knockout stages in unconvincing victory",
    "link": "https://www.independent.co.uk/sport/football/brighton-europa-league-var-domagoj-vida-marseille-b2456423.html",
    "pubDate": "Thu, 30 Nov 2023 22:58:24 GMT",
    "dc:creator": "Ed Elliot",
    "dc:date": "2023-11-30T22:58:24+00:00",
    "content": "<p>Pedro netted his fifth goal of the competition to guarantee the Seagulls a top-two finish in Group B</p>",
    "contentSnippet": "Pedro netted his fifth goal of the competition to guarantee the Seagulls a top-two finish in Group B",
    "guid": "b2456423",
    "categories": [
      "Football",
      "Sport"
    ],
    "isoDate": "2023-11-30T22:58:24.000Z"
  },
  {
    "creator": "Richard Jolly",
    "date": "2023-11-30T22:57:09+00:00",
    "title": "Liverpool’s Europa League job is done, but Mohamed Salah remains agonisingly short of a key milestone",
    "link": "https://www.independent.co.uk/sport/football/liverpool-mohamed-salah-europa-league-result-b2456482.html",
    "pubDate": "Thu, 30 Nov 2023 22:57:09 GMT",
    "dc:creator": "Richard Jolly",
    "dc:date": "2023-11-30T22:57:09+00:00",
    "content": "<p><strong>Liverpool 4-0 LASK:</strong> Mohamed Salah is just one goal away from joining the coveted 200 club at Liverpool </p>",
    "contentSnippet": "Liverpool 4-0 LASK: Mohamed Salah is just one goal away from joining the coveted 200 club at Liverpool",
    "guid": "b2456482",
    "categories": [
      "Football",
      "Sport"
    ],
    "isoDate": "2023-11-30T22:57:09.000Z"
  },
  {
    "creator": "Nick Mashiter",
    "date": "2023-11-30T22:54:57+00:00",
    "title": "Aston Villa progress in Europa Conference League but match overshadowed by fan violence",
    "link": "https://www.independent.co.uk/sport/football/aston-villa-legia-warsaw-europa-conference-league-youri-tielemans-villarreal-b2456485.html",
    "pubDate": "Thu, 30 Nov 2023 22:54:57 GMT",
    "dc:creator": "Nick Mashiter",
    "dc:date": "2023-11-30T22:54:57+00:00",
    "content": "<p>Villa moved top of Group E after victory over Legia Warsaw</p>",
    "contentSnippet": "Villa moved top of Group E after victory over Legia Warsaw",
    "guid": "b2456485",
    "categories": [
      "Football",
      "Sport"
    ],
    "isoDate": "2023-11-30T22:54:57.000Z"
  },
  {
    "creator": "Alex Woodward",
    "date": "2023-11-30T22:54:08+00:00",
    "title": "Trump immediately attacks judge’s wife after gag order reinstated in fraud trial",
    "link": "https://www.the-independent.com/news/world/americas/us-politics/trump-arthur-engoron-wife-gag-order-b2456499.html",
    "pubDate": "Thu, 30 Nov 2023 22:54:08 GMT",
    "dc:creator": "Alex Woodward",
    "dc:date": "2023-11-30T22:54:08+00:00",
    "content": "<p>A recent court filing warned that credible threats from the former president’s attacks posed an ‘ongoing security risk’ for the judge, his staff and family</p>",
    "contentSnippet": "A recent court filing warned that credible threats from the former president’s attacks posed an ‘ongoing security risk’ for the judge, his staff and family",
    "guid": "b2456499",
    "categories": [
      "US politics",
      "Americas",
      "World"
    ],
    "isoDate": "2023-11-30T22:54:08.000Z"
  },
  {
    "creator": "Michael Goldberg",
    "date": "2023-11-30T22:52:45+00:00",
    "title": "Mississippi Supreme Court delays decision on whether to set execution date for man on death row",
    "link": "https://www.independent.co.uk/news/ap-jackson-mississippi-attorney-general-fbi-b2456513.html",
    "pubDate": "Thu, 30 Nov 2023 22:52:45 GMT",
    "dc:creator": "Michael Goldberg",
    "dc:date": "2023-11-30T22:52:45+00:00",
    "content": "The Mississippi Supreme Court has temporarily delayed ruling on whether to set an execution date for a man on death row for capital murder",
    "contentSnippet": "The Mississippi Supreme Court has temporarily delayed ruling on whether to set an execution date for a man on death row for capital murder",
    "guid": "b2456513",
    "isoDate": "2023-11-30T22:52:45.000Z"
  },
  {
    "creator": "Pa Sport Staff",
    "date": "2023-11-30T22:50:57+00:00",
    "title": "Liverpool, Brighton and West Ham all secure place in the Europa League knockout stages",
    "link": "https://www.independent.co.uk/sport/football/liverpool-brighton-west-ham-europa-league-b2456508.html",
    "pubDate": "Thu, 30 Nov 2023 22:50:57 GMT",
    "dc:creator": "Pa Sport Staff",
    "dc:date": "2023-11-30T22:50:57+00:00",
    "content": "<p>Brighton, West Ham and Liverpool all qualified from their Europa League groups </p>",
    "contentSnippet": "Brighton, West Ham and Liverpool all qualified from their Europa League groups",
    "guid": "b2456508",
    "categories": [
      "Football",
      "Sport"
    ],
    "isoDate": "2023-11-30T22:50:57.000Z"
  },
  {
    "creator": "Jonel Aleccia",
    "date": "2023-11-30T22:50:53+00:00",
    "title": "Don't eat pre-cut cantaloupe if the source is unknown, CDC says, as deadly salmonella outbreak grows",
    "link": "https://www.independent.co.uk/news/consumers-ap-cdc-trader-joes-canada-b2456512.html",
    "pubDate": "Thu, 30 Nov 2023 22:50:53 GMT",
    "dc:creator": "Jonel Aleccia",
    "dc:date": "2023-11-30T22:50:53+00:00",
    "content": "U.S. health officials say consumers should not eat pre-cut cantaloupe if they don’t know the source",
    "contentSnippet": "U.S. health officials say consumers should not eat pre-cut cantaloupe if they don’t know the source",
    "guid": "b2456512",
    "isoDate": "2023-11-30T22:50:53.000Z"
  },
  {
    "creator": "Rhys Jones",
    "date": "2023-11-30T22:50:17+00:00",
    "title": "Cop28 president and oil executive opens climate conference",
    "link": "https://www.independent.co.uk/tv/news/cop28-sultan-al-jaber-climate-action-b2456429.html",
    "pubDate": "Thu, 30 Nov 2023 22:50:17 GMT",
    "dc:creator": "Rhys Jones",
    "dc:date": "2023-11-30T22:50:17+00:00",
    "content": "<p>Sultan al-Jaber, CEO of one of the world’s largest oil companies and <a href=\"/topic/cop28\">Cop28</a> president, opened the climate conference in the <a href=\"/topic/united-arab-emirates\">United Arab Emirates</a> on Thursday, 30 November.</p>",
    "contentSnippet": "Sultan al-Jaber, CEO of one of the world’s largest oil companies and Cop28 president, opened the climate conference in the United Arab Emirates on Thursday, 30 November.",
    "guid": "b2456429",
    "categories": [
      "News",
      "Indy TV"
    ],
    "isoDate": "2023-11-30T22:50:17.000Z"
  },
  {
    "creator": "Roisin O'Connor,Nicole Vassell and Inga Parkel",
    "date": "2023-11-30T22:49:36+00:00",
    "title": "Beyoncé’s Renaissance – live: Inside the London premiere of her record-breaking world tour",
    "link": "https://www.independent.co.uk/arts-entertainment/music/news/beyonce-renaissance-london-live-red-carpet-b2456107.html",
    "pubDate": "Thu, 30 Nov 2023 22:49:36 GMT",
    "dc:creator": "Roisin O'Connor,Nicole Vassell and Inga Parkel",
    "dc:date": "2023-11-30T22:49:36+00:00",
    "content": "<p>US star premiered the concert film about her record-breaking 2023 tour </p>",
    "contentSnippet": "US star premiered the concert film about her record-breaking 2023 tour",
    "guid": "b2456107",
    "categories": [
      "News",
      "Music",
      "Culture"
    ],
    "isoDate": "2023-11-30T22:49:36.000Z"
  },
  {
    "creator": "Andrea Cavallier",
    "date": "2023-11-30T22:48:55+00:00",
    "title": "Lori Vallow seen in new mug shot after ‘very chatty’ extradition trip to Arizona",
    "link": "https://www.the-independent.com/news/world/americas/crime/lori-vallow-mugshot-murder-trial-b2456259.html",
    "pubDate": "Thu, 30 Nov 2023 22:48:55 GMT",
    "dc:creator": "Andrea Cavallier",
    "dc:date": "2023-11-30T22:48:55+00:00",
    "content": "<p>Lori faces charges of conspiring to kill her fourth husband Charles Vallow in Arizona </p>",
    "contentSnippet": "Lori faces charges of conspiring to kill her fourth husband Charles Vallow in Arizona",
    "guid": "b2456259",
    "categories": [
      "US Crime News",
      "Americas",
      "World"
    ],
    "isoDate": "2023-11-30T22:48:55.000Z"
  },
  {
    "creator": "Graeme Massie",
    "date": "2023-11-30T22:43:04+00:00",
    "title": "Social justice charity founder killed in LA home invasion",
    "link": "https://www.the-independent.com/news/world/americas/crime/latt-home-invasion-shooting-death-b2456389.html",
    "pubDate": "Thu, 30 Nov 2023 22:43:04 GMT",
    "dc:creator": "Graeme Massie",
    "dc:date": "2023-11-30T22:43:04+00:00",
    "content": "<p>Prosecutors say Michael Latt targetted because he was friend of woman allegedly stalked by suspect </p>",
    "contentSnippet": "Prosecutors say Michael Latt targetted because he was friend of woman allegedly stalked by suspect",
    "guid": "b2456389",
    "categories": [
      "US Crime News",
      "Americas",
      "World"
    ],
    "isoDate": "2023-11-30T22:43:04.000Z"
  },
  {
    "creator": "Patrick Daly",
    "date": "2023-11-30T22:40:32+00:00",
    "title": "A Labour government would consider new powers to prevent ‘banking deserts’",
    "link": "https://www.independent.co.uk/money/a-labour-government-would-consider-new-powers-to-prevent-banking-deserts-b2456498.html",
    "pubDate": "Thu, 30 Nov 2023 22:40:32 GMT",
    "dc:creator": "Patrick Daly",
    "dc:date": "2023-11-30T22:40:32+00:00",
    "content": "Shadow chancellor Rachel Reeves said her party wants to ensure ‘every community has access to high street banking services’.",
    "contentSnippet": "Shadow chancellor Rachel Reeves said her party wants to ensure ‘every community has access to high street banking services’.",
    "guid": "b2456498",
    "categories": [
      "Money"
    ],
    "isoDate": "2023-11-30T22:40:32.000Z"
  },
  {
    "creator": "Rhys Jones",
    "date": "2023-11-30T22:33:49+00:00",
    "title": "White lion cubs born in Venezuela with less than 200 left in the world",
    "link": "https://www.independent.co.uk/tv/news/white-lion-cubs-venezuela-b2456480.html",
    "pubDate": "Thu, 30 Nov 2023 22:33:49 GMT",
    "dc:creator": "Rhys Jones",
    "dc:date": "2023-11-30T22:33:49+00:00",
    "content": "<p>Three white <a href=\"/topic/lions\">lion</a> cubs were born in <a href=\"/topic/venezuela\">Venezuela</a> on  Wednesday 29 November.</p>",
    "contentSnippet": "Three white lion cubs were born in Venezuela on  Wednesday 29 November.",
    "guid": "b2456480",
    "categories": [
      "News",
      "Indy TV"
    ],
    "isoDate": "2023-11-30T22:33:49.000Z"
  },
  {
    "creator": "Mike Bedigan",
    "date": "2023-11-30T22:32:08+00:00",
    "title": "College football player dies after collapsing during team weights session",
    "link": "https://www.independent.co.uk/news/world/americas/reed-ryan-college-football-cardiac-arrest-b2456459.html",
    "pubDate": "Thu, 30 Nov 2023 22:32:08 GMT",
    "dc:creator": "Mike Bedigan",
    "dc:date": "2023-11-30T22:32:08+00:00",
    "content": "<p>A college football player has died at the age of 22, a week after suffering a cardiac arrest during a team weights session.</p>",
    "contentSnippet": "A college football player has died at the age of 22, a week after suffering a cardiac arrest during a team weights session.",
    "guid": "b2456459",
    "categories": [
      "Americas",
      "World"
    ],
    "isoDate": "2023-11-30T22:32:08.000Z"
  },
  {
    "creator": "Larry Neumeister",
    "date": "2023-11-30T22:30:17+00:00",
    "title": "US prosecutors say plots to assassinate Sikh leaders were part of a campaign of planned killings",
    "link": "https://www.independent.co.uk/news/ap-hardeep-singh-nijjar-india-sikh-new-york-b2456505.html",
    "pubDate": "Thu, 30 Nov 2023 22:30:17 GMT",
    "dc:creator": "Larry Neumeister",
    "dc:date": "2023-11-30T22:30:17+00:00",
    "content": "Law enforcement authorities say in court papers that the plot driven by a government official in India to assassinate a prominent Sikh separatist leader in New York City was meant to precede another killing in California and more assassinations in the U.S. and Canada",
    "contentSnippet": "Law enforcement authorities say in court papers that the plot driven by a government official in India to assassinate a prominent Sikh separatist leader in New York City was meant to precede another killing in California and more assassinations in the U.S. and Canada",
    "guid": "b2456505",
    "isoDate": "2023-11-30T22:30:17.000Z"
  },
  {
    "creator": "David Hughes",
    "date": "2023-11-30T22:30:00+00:00",
    "title": "Starmer: Transition to net zero can ‘turbo-charge growth’",
    "link": "https://www.independent.co.uk/business/starmer-transition-to-net-zero-can-turbocharge-growth-b2456497.html",
    "pubDate": "Thu, 30 Nov 2023 22:30:00 GMT",
    "dc:creator": "David Hughes",
    "dc:date": "2023-11-30T22:30:00+00:00",
    "content": "Labour leader Sir Keir Starmer is in Dubai for the Cop28 climate summit.",
    "contentSnippet": "Labour leader Sir Keir Starmer is in Dubai for the Cop28 climate summit.",
    "guid": "b2456497",
    "categories": [
      "Business"
    ],
    "isoDate": "2023-11-30T22:30:00.000Z"
  },
  {
    "creator": "Wayne Parry",
    "date": "2023-11-30T22:27:23+00:00",
    "title": "Casino workers seethe as smoking ban bill is delayed yet again in New Jersey Legislature",
    "link": "https://www.independent.co.uk/news/world/americas/atlantic-city-ap-trenton-phil-murphy-democratic-b2456502.html",
    "pubDate": "Thu, 30 Nov 2023 22:27:23 GMT",
    "dc:creator": "Wayne Parry",
    "dc:date": "2023-11-30T22:27:23+00:00",
    "content": "A bill that would end smoking in Atlantic City's casinos continues to go nowhere",
    "contentSnippet": "A bill that would end smoking in Atlantic City's casinos continues to go nowhere",
    "guid": "b2456502",
    "categories": [
      "Americas",
      "World"
    ],
    "isoDate": "2023-11-30T22:27:23.000Z"
  },
  {
    "creator": "Via AP news wire",
    "date": "2023-11-30T22:26:37+00:00",
    "title": "Mom convicted of killing kids in Idaho taken to Arizona in murder conspiracy case",
    "link": "https://www.independent.co.uk/news/ap-arizona-idaho-chad-daybell-phoenix-b2456501.html",
    "pubDate": "Thu, 30 Nov 2023 22:26:37 GMT",
    "dc:creator": "Via AP news wire",
    "dc:date": "2023-11-30T22:26:37+00:00",
    "content": "A woman is in an Arizona jail facing charges in a killing after she was sentenced to life in an Idaho prison for murdering her two youngest children and another woman",
    "contentSnippet": "A woman is in an Arizona jail facing charges in a killing after she was sentenced to life in an Idaho prison for murdering her two youngest children and another woman",
    "guid": "b2456501",
    "isoDate": "2023-11-30T22:26:37.000Z"
  },
  {
    "creator": "Scott Bauer",
    "date": "2023-11-30T22:23:47+00:00",
    "title": "Unions in Wisconsin sue to reverse collective bargaining restrictions on teachers, others",
    "link": "https://www.independent.co.uk/news/wisconsin-ap-scott-walker-unions-republican-b2456494.html",
    "pubDate": "Thu, 30 Nov 2023 22:23:47 GMT",
    "dc:creator": "Scott Bauer",
    "dc:date": "2023-11-30T22:23:47+00:00",
    "content": "Seven unions representing teachers and other public workers in Wisconsin have filed a lawsuit attempting to end the state’s near-total ban on collective bargaining for most public employees",
    "contentSnippet": "Seven unions representing teachers and other public workers in Wisconsin have filed a lawsuit attempting to end the state’s near-total ban on collective bargaining for most public employees",
    "guid": "b2456494",
    "isoDate": "2023-11-30T22:23:47.000Z"
  },
  {
    "creator": "Freida Frisaro and David Fischer",
    "date": "2023-11-30T22:20:13+00:00",
    "title": "Hurricane season that saw storms from California to Nova Scotia ends Thursday",
    "link": "https://www.independent.co.uk/news/ap-southern-california-nova-scotia-fort-lauderdale-national-hurricane-center-b2456496.html",
    "pubDate": "Thu, 30 Nov 2023 22:20:13 GMT",
    "dc:creator": "Freida Frisaro and David Fischer",
    "dc:date": "2023-11-30T22:20:13+00:00",
    "content": "A busy Atlantic hurricane season is now coming to a close",
    "contentSnippet": "A busy Atlantic hurricane season is now coming to a close",
    "guid": "b2456496",
    "isoDate": "2023-11-30T22:20:13.000Z"
  },
  {
    "creator": "Mead Gruver",
    "date": "2023-11-30T22:20:07+00:00",
    "title": "Family of Marine killed in Afghanistan fails to win lawsuit against Alec Baldwin",
    "link": "https://www.independent.co.uk/news/ap-alec-baldwin-family-wyo-afghanistan-b2456495.html",
    "pubDate": "Thu, 30 Nov 2023 22:20:07 GMT",
    "dc:creator": "Mead Gruver",
    "dc:date": "2023-11-30T22:20:07+00:00",
    "content": "A lawsuit against Alec Baldwin filed by relatives of a U.S. Marine killed in Afghanistan has been resolved in the actor's favor",
    "contentSnippet": "A lawsuit against Alec Baldwin filed by relatives of a U.S. Marine killed in Afghanistan has been resolved in the actor's favor",
    "guid": "b2456495",
    "isoDate": "2023-11-30T22:20:07.000Z"
  },
  {
    "creator": "Pa Sport Staff",
    "date": "2023-11-30T22:20:07+00:00",
    "title": "Tiger Woods admits Hero World Challenge comeback comes at a cost",
    "link": "https://www.independent.co.uk/sport/golf/tiger-woods-hero-world-challenge-golf-return-b2456490.html",
    "pubDate": "Thu, 30 Nov 2023 22:20:07 GMT",
    "dc:creator": "Pa Sport Staff",
    "dc:date": "2023-11-30T22:20:07+00:00",
    "content": "<p> </p>",
    "contentSnippet": "",
    "guid": "b2456490",
    "categories": [
      "Golf",
      "Sport"
    ],
    "isoDate": "2023-11-30T22:20:07.000Z"
  },
  {
    "creator": "Via AP news wire",
    "date": "2023-11-30T22:18:08+00:00",
    "title": "Sen. Rand Paul performed Heimlich maneuver on choking Sen. Joni Ernst during GOP lunch",
    "link": "https://www.independent.co.uk/news/joni-ernst-ap-rand-paul-washington-gop-b2456492.html",
    "pubDate": "Thu, 30 Nov 2023 22:18:08 GMT",
    "dc:creator": "Via AP news wire",
    "dc:date": "2023-11-30T22:18:08+00:00",
    "content": "Sen. Joni Ernst, a Republican from Iowa, was choking on food during a luncheon when fellow Republican Sen. Rand Paul of Kentucky performed the Heimlich maneuver on her",
    "contentSnippet": "Sen. Joni Ernst, a Republican from Iowa, was choking on food during a luncheon when fellow Republican Sen. Rand Paul of Kentucky performed the Heimlich maneuver on her",
    "guid": "b2456492",
    "isoDate": "2023-11-30T22:18:08.000Z"
  },
  {
    "creator": "Maryam Zakir-Hussain",
    "date": "2023-11-30T22:14:27+00:00",
    "title": "Dutch translator of Omid Scobie’s Endgame denies making error: ‘The names were there in black and white’",
    "link": "https://www.independent.co.uk/news/uk/home-news/endgame-royal-racism-row-dutch-translator-b2456475.html",
    "pubDate": "Thu, 30 Nov 2023 22:14:27 GMT",
    "dc:creator": "Maryam Zakir-Hussain",
    "dc:date": "2023-11-30T22:14:27+00:00",
    "content": "<p>Royal author Omid Scobie insists he never submitted a book with names in it as Endgame fallout continues </p>",
    "contentSnippet": "Royal author Omid Scobie insists he never submitted a book with names in it as Endgame fallout continues",
    "guid": "b2456475",
    "categories": [
      "Home News",
      "UK"
    ],
    "isoDate": "2023-11-30T22:14:27.000Z"
  },
  {
    "creator": "Rhys Jones",
    "date": "2023-11-30T22:13:34+00:00",
    "title": "I’m A Celeb: Sam Thompson opens up about ADHD diagnosis",
    "link": "https://www.independent.co.uk/tv/lifestyle/adhd-sam-thompson-diagnosis-b2456478.html",
    "pubDate": "Thu, 30 Nov 2023 22:13:34 GMT",
    "dc:creator": "Rhys Jones",
    "dc:date": "2023-11-30T22:13:34+00:00",
    "content": "<p>I’m a Celebrity’s <a href=\"/topic/sam-thompson\">Sam Thompson</a> opened up on being diagnosed with <a href=\"/topic/adhd\">ADHD</a> as an adult and how it’s affected him.</p>",
    "contentSnippet": "I’m a Celebrity’s Sam Thompson opened up on being diagnosed with ADHD as an adult and how it’s affected him.",
    "guid": "b2456478",
    "categories": [
      "Lifestyle",
      "Indy TV"
    ],
    "isoDate": "2023-11-30T22:13:34.000Z"
  },
  {
    "creator": "Carl Markham",
    "date": "2023-11-30T22:11:29+00:00",
    "title": "Mohamed Salah closes in on 200 club as Liverpool confirm top spot",
    "link": "https://www.independent.co.uk/sport/football/mohamed-salah-liverpool-jurgen-klopp-luis-diaz-joe-gomez-b2456484.html",
    "pubDate": "Thu, 30 Nov 2023 22:11:29 GMT",
    "dc:creator": "Carl Markham",
    "dc:date": "2023-11-30T22:11:29+00:00",
    "content": "The Reds eased to a 4-0 Europa League victory against LASK at Anfield.",
    "contentSnippet": "The Reds eased to a 4-0 Europa League victory against LASK at Anfield.",
    "guid": "b2456484",
    "categories": [
      "Football",
      "Sport"
    ],
    "isoDate": "2023-11-30T22:11:29.000Z"
  },
  {
    "creator": "Via AP news wire",
    "date": "2023-11-30T22:10:08+00:00",
    "title": "Facebook parent Meta sues the FTC claiming 'unconstitutional authority' in child privacy case",
    "link": "https://www.independent.co.uk/news/meta-ap-ftc-facebook-menlo-park-b2456489.html",
    "pubDate": "Thu, 30 Nov 2023 22:10:08 GMT",
    "dc:creator": "Via AP news wire",
    "dc:date": "2023-11-30T22:10:08+00:00",
    "content": "The parent company of Instagram and Facebook has sued the Federal Trade Commission in an attempt to stop the agency from reopening a 2020 privacy settlement with the company that would prohibit it from profiting from data it collects on users under 18",
    "contentSnippet": "The parent company of Instagram and Facebook has sued the Federal Trade Commission in an attempt to stop the agency from reopening a 2020 privacy settlement with the company that would prohibit it from profiting from data it collects on users under 18",
    "guid": "b2456489",
    "isoDate": "2023-11-30T22:10:08.000Z"
  },
  {
    "creator": "Rhys Jones",
    "date": "2023-11-30T22:06:03+00:00",
    "title": "Taylor Swift attends Beyonce’s ‘Renaissance’ World Tour film premiere in London",
    "link": "https://www.independent.co.uk/tv/culture/taylor-swift-beyonce-renaissance-b2456483.html",
    "pubDate": "Thu, 30 Nov 2023 22:06:03 GMT",
    "dc:creator": "Rhys Jones",
    "dc:date": "2023-11-30T22:06:03+00:00",
    "content": "<p><a href=\"/topic/taylor-swift\">Taylor Swift</a> attended <a href=\"/topic/beyonce\">Beyonce</a>’s ‘Renaissance’ World Tour film premiere in London on Thursday 30 November.</p>",
    "contentSnippet": "Taylor Swift attended Beyonce’s ‘Renaissance’ World Tour film premiere in London on Thursday 30 November.",
    "guid": "b2456483",
    "categories": [
      "Culture",
      "Indy TV"
    ],
    "isoDate": "2023-11-30T22:06:03.000Z"
  },
  {
    "creator": "Gustaf Kilander",
    "date": "2023-11-30T22:04:30+00:00",
    "title": "George Santos decries ‘bullying’ ahead of expulsion vote: Latest",
    "link": "https://www.independent.co.uk/news/world/americas/george-santos-news-vote-expulsion-latest-b2455996.html",
    "pubDate": "Thu, 30 Nov 2023 22:04:30 GMT",
    "dc:creator": "Gustaf Kilander",
    "dc:date": "2023-11-30T22:04:30+00:00",
    "content": "<p>Republicans unlikely to back Democratic resolution to oust 35-year-old, instead looking to GOP Ethics panel chair to take action </p>",
    "contentSnippet": "Republicans unlikely to back Democratic resolution to oust 35-year-old, instead looking to GOP Ethics panel chair to take action",
    "guid": "b2455996",
    "categories": [
      "Americas",
      "World"
    ],
    "isoDate": "2023-11-30T22:04:30.000Z"
  },
  {
    "creator": "Graig Graziosi",
    "date": "2023-11-30T22:02:13+00:00",
    "title": "McCarthy says Gaetz ‘belongs in jail’ in latest spat between Republican enemies",
    "link": "https://www.the-independent.com/news/world/americas/us-politics/kevin-mccarthy-matt-gaetz-jail-republicans-b2456469.html",
    "pubDate": "Thu, 30 Nov 2023 22:02:13 GMT",
    "dc:creator": "Graig Graziosi",
    "dc:date": "2023-11-30T22:02:13+00:00",
    "content": "<p>Mr McCarthy may be considering resigning from Congress, according to a recent report </p>",
    "contentSnippet": "Mr McCarthy may be considering resigning from Congress, according to a recent report",
    "guid": "b2456469",
    "categories": [
      "US politics",
      "Americas",
      "World"
    ],
    "isoDate": "2023-11-30T22:02:13.000Z"
  },
  {
    "creator": "Amber Raiken",
    "date": "2023-11-30T22:01:29+00:00",
    "title": "Beyoncé honours late uncle with release of Renaissance film on Aids Day",
    "link": "https://www.independent.co.uk/life-style/beyonce-renaissance-film-aids-day-b2456365.html",
    "pubDate": "Thu, 30 Nov 2023 22:01:29 GMT",
    "dc:creator": "Amber Raiken",
    "dc:date": "2023-11-30T22:01:29+00:00",
    "content": "<p>Concert film is hitting theatres on 1 December  </p>",
    "contentSnippet": "Concert film is hitting theatres on 1 December",
    "guid": "b2456365",
    "categories": [
      "Lifestyle"
    ],
    "isoDate": "2023-11-30T22:01:29.000Z"
  },
  {
    "creator": "Via AP news wire",
    "date": "2023-11-30T21:58:59+00:00",
    "title": "Cockpit voice recordings get erased after some close calls. The FAA will try to fix that",
    "link": "https://www.independent.co.uk/news/faa-ap-washington-american-airlines-delta-air-lines-b2456481.html",
    "pubDate": "Thu, 30 Nov 2023 21:58:59 GMT",
    "dc:creator": "Via AP news wire",
    "dc:date": "2023-11-30T21:58:59+00:00",
    "content": "Federal officials say they will give investigators a better tool for understanding accidents and close calls between planes",
    "contentSnippet": "Federal officials say they will give investigators a better tool for understanding accidents and close calls between planes",
    "guid": "b2456481",
    "isoDate": "2023-11-30T21:58:59.000Z"
  },
  {
    "creator": "Sheila Flynn",
    "date": "2023-11-30T21:57:32+00:00",
    "title": "Taylor Swift’s biggest fans: Meet the Swifties in Spotify’s top .001% of listeners",
    "link": "https://www.independent.co.uk/news/world/americas/taylor-swift-spotify-wrapped-travis-kelce-b2456368.html",
    "pubDate": "Thu, 30 Nov 2023 21:57:32 GMT",
    "dc:creator": "Sheila Flynn",
    "dc:date": "2023-11-30T21:57:32+00:00",
    "content": "<p>The top tier of listeners of the top-streamed artist spent more than two-thirds of the year streaming Taylor Swift on Spotify, reports  <strong>Sheila Flynn </strong></p>",
    "contentSnippet": "The top tier of listeners of the top-streamed artist spent more than two-thirds of the year streaming Taylor Swift on Spotify, reports  Sheila Flynn",
    "guid": "b2456368",
    "categories": [
      "Americas",
      "World"
    ],
    "isoDate": "2023-11-30T21:57:32.000Z"
  },
  {
    "creator": "Jane Dalton",
    "date": "2023-11-30T21:55:49+00:00",
    "title": "UK weather – live: Temperatures plunge below zero as big freeze set to bring snow and ice",
    "link": "https://www.independent.co.uk/weather/snow-forecast-uk-weather-met-office-b2455964.html",
    "pubDate": "Thu, 30 Nov 2023 21:55:49 GMT",
    "dc:creator": "Jane Dalton",
    "dc:date": "2023-11-30T21:55:49+00:00",
    "content": "<p>Severe weather warnings in place as rough sleepers offered emergency beds </p>",
    "contentSnippet": "Severe weather warnings in place as rough sleepers offered emergency beds",
    "guid": "b2455964",
    "categories": [
      "Weather"
    ],
    "isoDate": "2023-11-30T21:55:49.000Z"
  },
  {
    "creator": "Anthony Cuthbertson",
    "date": "2023-11-30T21:46:32+00:00",
    "title": "Google issues final warning to Gmail account holders",
    "link": "https://www.independent.co.uk/tech/gmail-account-warning-google-deadline-b2452371.html",
    "pubDate": "Thu, 30 Nov 2023 21:46:32 GMT",
    "dc:creator": "Anthony Cuthbertson",
    "dc:date": "2023-11-30T21:46:32+00:00",
    "content": "<p>Users warned that documents, emails and photos are all at risk of mass purge </p>",
    "contentSnippet": "Users warned that documents, emails and photos are all at risk of mass purge",
    "guid": "b2452371",
    "categories": [
      "Tech"
    ],
    "isoDate": "2023-11-30T21:46:32.000Z"
  },
  {
    "creator": "Gabriela Selser",
    "date": "2023-11-30T21:44:59+00:00",
    "title": "A new study says about half of Nicaragua's population wants to emigrate",
    "link": "https://www.independent.co.uk/news/ap-daniel-ortega-nicaragua-mexico-city-americas-b2456479.html",
    "pubDate": "Thu, 30 Nov 2023 21:44:59 GMT",
    "dc:creator": "Gabriela Selser",
    "dc:date": "2023-11-30T21:44:59+00:00",
    "content": "A new study says that about half of Nicaragua's population of 6.2 million want to leave their homeland because of a mix of economic decline and repression from President Daniel Ortega's government",
    "contentSnippet": "A new study says that about half of Nicaragua's population of 6.2 million want to leave their homeland because of a mix of economic decline and repression from President Daniel Ortega's government",
    "guid": "b2456479",
    "isoDate": "2023-11-30T21:44:59.000Z"
  },
  {
    "creator": "Olivia Hebert",
    "date": "2023-11-30T21:40:59+00:00",
    "title": "Kelly Clarkson’s ex-husband Brandon Blackstock must pay her after overcharging her as manager",
    "link": "https://www.independent.co.uk/life-style/kelly-clarkson-ex-husband-manager-brandon-blackstock-b2456353.html",
    "pubDate": "Thu, 30 Nov 2023 21:40:59 GMT",
    "dc:creator": "Olivia Hebert",
    "dc:date": "2023-11-30T21:40:59+00:00",
    "content": "<p>Singer’s ex-husband and former manager has been ordered to return more than $2m to her </p>",
    "contentSnippet": "Singer’s ex-husband and former manager has been ordered to return more than $2m to her",
    "guid": "b2456353",
    "categories": [
      "Lifestyle"
    ],
    "isoDate": "2023-11-30T21:40:59.000Z"
  },
  {
    "creator": "Tom Bennett",
    "date": "2023-11-30T21:39:49+00:00",
    "title": "More Hamas hostages released from inside Gaza – with Palestinians in Israeli prisons also set to be freed",
    "link": "https://www.independent.co.uk/news/world/middle-east/israel-hamas-hostages-gaza-jerusalem-b2456386.html",
    "pubDate": "Thu, 30 Nov 2023 21:39:49 GMT",
    "dc:creator": "Tom Bennett",
    "dc:date": "2023-11-30T21:39:49+00:00",
    "content": "<p>Latest exchange comes after shooting in Jerusalem – claimed by Hamas – that killed three. One of those wounded says he feels ‘lucky’ to be alive  </p>",
    "contentSnippet": "Latest exchange comes after shooting in Jerusalem – claimed by Hamas – that killed three. One of those wounded says he feels ‘lucky’ to be alive",
    "guid": "b2456386",
    "categories": [
      "Middle East",
      "World"
    ],
    "isoDate": "2023-11-30T21:39:49.000Z"
  },
  {
    "creator": "Ed Elliot",
    "date": "2023-11-30T21:39:10+00:00",
    "title": "You’ve got to dream big: Lewis Dunk eyes Europa League glory with Brighton",
    "link": "https://www.independent.co.uk/sport/football/lewis-dunk-europa-league-marseille-greek-league-one-b2456476.html",
    "pubDate": "Thu, 30 Nov 2023 21:39:10 GMT",
    "dc:creator": "Ed Elliot",
    "dc:date": "2023-11-30T21:39:10+00:00",
    "content": "Albion have guaranteed a top-two finish in Group B with a game to spare.",
    "contentSnippet": "Albion have guaranteed a top-two finish in Group B with a game to spare.",
    "guid": "b2456476",
    "categories": [
      "Football",
      "Sport"
    ],
    "isoDate": "2023-11-30T21:39:10.000Z"
  },
  {
    "creator": "Rhys Jones",
    "date": "2023-11-30T21:38:05+00:00",
    "title": "Police injured by Legia Warsaw fans ahead of game at Aston Villa",
    "link": "https://www.independent.co.uk/tv/sport/aston-villa-legia-warsaw-fans-police-b2456472.html",
    "pubDate": "Thu, 30 Nov 2023 21:38:05 GMT",
    "dc:creator": "Rhys Jones",
    "dc:date": "2023-11-30T21:38:05+00:00",
    "content": "<p>Three police officers have reportedly been injured outside <a href=\"/topic/villa-park\">Villa Park</a> after missiles were thrown at them by <a href=\"/topic/legia-warsaw\">Legia Warsaw</a> fans on Thursday 30 November.</p>",
    "contentSnippet": "Three police officers have reportedly been injured outside Villa Park after missiles were thrown at them by Legia Warsaw fans on Thursday 30 November.",
    "guid": "b2456472",
    "categories": [
      "Sport",
      "Indy TV"
    ],
    "isoDate": "2023-11-30T21:38:05.000Z"
  },
  {
    "creator": "Darlene Superville",
    "date": "2023-11-30T21:36:42+00:00",
    "title": "Biden gets a chance to bring holiday spirit to Washington by lighting the National Christmas Tree",
    "link": "https://www.independent.co.uk/news/joe-biden-ap-washington-kamala-harris-doug-emhoff-b2456477.html",
    "pubDate": "Thu, 30 Nov 2023 21:36:42 GMT",
    "dc:creator": "Darlene Superville",
    "dc:date": "2023-11-30T21:36:42+00:00",
    "content": "President Joe Biden is getting a turn at bringing the holiday spirit to Washington",
    "contentSnippet": "President Joe Biden is getting a turn at bringing the holiday spirit to Washington",
    "guid": "b2456477",
    "isoDate": "2023-11-30T21:36:42.000Z"
  },
  {
    "creator": "Rachel Sharp and Ariana Baio",
    "date": "2023-11-30T21:33:02+00:00",
    "title": "As controversial in death as in life: Tributes pour in for Henry Kissinger",
    "link": "https://www.independent.co.uk/news/world/americas/henry-kissinger-controversy-tributes-b2456258.html",
    "pubDate": "Thu, 30 Nov 2023 21:33:02 GMT",
    "dc:creator": "Rachel Sharp and Ariana Baio",
    "dc:date": "2023-11-30T21:33:02+00:00",
    "content": "<p>Tributes and statements have begun pouring in for the influential US diplomat after he died aged 100 at his Connecticut home on Wednesday </p>",
    "contentSnippet": "Tributes and statements have begun pouring in for the influential US diplomat after he died aged 100 at his Connecticut home on Wednesday",
    "guid": "b2456258",
    "categories": [
      "Americas",
      "World"
    ],
    "isoDate": "2023-11-30T21:33:02.000Z"
  },
  {
    "creator": "Olivia Hebert",
    "date": "2023-11-30T21:21:10+00:00",
    "title": "Taylor Swift stuns at Beyoncé’s Renaissance film premiere in London",
    "link": "https://www.independent.co.uk/life-style/renaissance-film-beyonce-taylor-swift-b2456411.html",
    "pubDate": "Thu, 30 Nov 2023 21:21:10 GMT",
    "dc:creator": "Olivia Hebert",
    "dc:date": "2023-11-30T21:21:10+00:00",
    "content": "<p> ‘Anti-Hero’ singer showed up to support Beyoncé’ for her London film premiere </p>",
    "contentSnippet": "‘Anti-Hero’ singer showed up to support Beyoncé’ for her London film premiere",
    "guid": "b2456411",
    "categories": [
      "Lifestyle"
    ],
    "isoDate": "2023-11-30T21:21:10.000Z"
  },
  {
    "creator": "Jim Salter",
    "date": "2023-11-30T21:16:36+00:00",
    "title": "Missouri prosecutor accuses 3 men of holding student from India captive and beating him",
    "link": "https://www.independent.co.uk/news/ap-india-missouri-charles-b2456471.html",
    "pubDate": "Thu, 30 Nov 2023 21:16:36 GMT",
    "dc:creator": "Jim Salter",
    "dc:date": "2023-11-30T21:16:36+00:00",
    "content": "A Missouri prosecutor says three men held a student from India captive over the course of several months and forced him to work and perform menial tasks, then viciously beat him when he didn’t complete the chores to their satisfaction",
    "contentSnippet": "A Missouri prosecutor says three men held a student from India captive over the course of several months and forced him to work and perform menial tasks, then viciously beat him when he didn’t complete the chores to their satisfaction",
    "guid": "b2456471",
    "isoDate": "2023-11-30T21:16:36.000Z"
  },
  {
    "creator": "John Bowden",
    "date": "2023-11-30T21:10:35+00:00",
    "title": "McCarthy claims he swore at Trump in tense phone call, report says",
    "link": "https://www.the-independent.com/news/world/americas/us-politics/mccarthy-trump-gaetz-gop-congress-b2456449.html",
    "pubDate": "Thu, 30 Nov 2023 21:10:35 GMT",
    "dc:creator": "John Bowden",
    "dc:date": "2023-11-30T21:10:35+00:00",
    "content": "<p>Ex-speaker has sought vengeance against political enemies following his ouster </p>",
    "contentSnippet": "Ex-speaker has sought vengeance against political enemies following his ouster",
    "guid": "b2456449",
    "categories": [
      "US politics",
      "Americas",
      "World"
    ],
    "isoDate": "2023-11-30T21:10:35.000Z"
  },
  {
    "creator": "Roisin O'Connor",
    "date": "2023-11-30T21:02:54+00:00",
    "title": "Shane MacGowan, shy and complex genius behind The Pogues, dies aged 65",
    "link": "https://www.independent.co.uk/arts-entertainment/music/news/shane-macgowan-death-age-pogues-news-b2456165.html",
    "pubDate": "Thu, 30 Nov 2023 21:02:54 GMT",
    "dc:creator": "Roisin O'Connor",
    "dc:date": "2023-11-30T21:02:54+00:00",
    "content": "<p>Musician had just returned home to be with his wife, Victoria Mary Clarke, after a lengthy stay in hospital </p>",
    "contentSnippet": "Musician had just returned home to be with his wife, Victoria Mary Clarke, after a lengthy stay in hospital",
    "guid": "b2456165",
    "categories": [
      "News",
      "Music",
      "Culture"
    ],
    "isoDate": "2023-11-30T21:02:54.000Z"
  },
  {
    "creator": "Via AP news wire",
    "date": "2023-11-30T20:52:38+00:00",
    "title": "Influential Detroit pastor the Rev. Charles Gilchrist Adams dies at age 86",
    "link": "https://www.independent.co.uk/news/ap-detroit-mike-duggan-harvard-university-boston-b2456464.html",
    "pubDate": "Thu, 30 Nov 2023 20:52:38 GMT",
    "dc:creator": "Via AP news wire",
    "dc:date": "2023-11-30T20:52:38+00:00",
    "content": "Influential longtime Detroit pastor the Rev. Charles Gilchrist Adams has died following an illness",
    "contentSnippet": "Influential longtime Detroit pastor the Rev. Charles Gilchrist Adams has died following an illness",
    "guid": "b2456464",
    "isoDate": "2023-11-30T20:52:38.000Z"
  },
  {
    "creator": "Via AP news wire",
    "date": "2023-11-30T20:49:16+00:00",
    "title": "Ferry operators around the country to receive $200M in federal grants to modernize fleets",
    "link": "https://www.independent.co.uk/news/ap-san-francisco-biden-new-york-maine-b2456462.html",
    "pubDate": "Thu, 30 Nov 2023 20:49:16 GMT",
    "dc:creator": "Via AP news wire",
    "dc:date": "2023-11-30T20:49:16+00:00",
    "content": "The Biden administration will issue $200 million in grants to modernize the country’s ferry systems",
    "contentSnippet": "The Biden administration will issue $200 million in grants to modernize the country’s ferry systems",
    "guid": "b2456462",
    "isoDate": "2023-11-30T20:49:16.000Z"
  },
  {
    "creator": "Bevan Hurley",
    "date": "2023-11-30T20:48:06+00:00",
    "title": "From Cambodia to Bangladesh: a brief history of Henry Kissinger’s alleged war crimes",
    "link": "https://www.independent.co.uk/news/world/americas/henry-kissinger-war-crimes-cambodia-b2456372.html",
    "pubDate": "Thu, 30 Nov 2023 20:48:06 GMT",
    "dc:creator": "Bevan Hurley",
    "dc:date": "2023-11-30T20:48:06+00:00",
    "content": "<p>Henry Kissinger sided with military dictators and genocidal regimes in his pursuit of projecting US power during the Cold War, resulting in the deaths of millions of innocents, Bevan Hurley reports</p>",
    "contentSnippet": "Henry Kissinger sided with military dictators and genocidal regimes in his pursuit of projecting US power during the Cold War, resulting in the deaths of millions of innocents, Bevan Hurley reports",
    "guid": "b2456372",
    "categories": [
      "Americas",
      "World"
    ],
    "isoDate": "2023-11-30T20:48:06.000Z"
  },
  {
    "creator": "Graig Graziosi",
    "date": "2023-11-30T20:46:42+00:00",
    "title": "GOP lawmaker makes not-so-veiled threat against Jack Smith",
    "link": "https://www.the-independent.com/news/world/americas/us-politics/clay-higgins-jack-smith-days-are-numbered-threat-b2456401.html",
    "pubDate": "Thu, 30 Nov 2023 20:46:42 GMT",
    "dc:creator": "Graig Graziosi",
    "dc:date": "2023-11-30T20:46:42+00:00",
    "content": "<p>Mr Higgins previously threatened FBI Director Chris Wray, telling him ‘your day is coming’ </p>",
    "contentSnippet": "Mr Higgins previously threatened FBI Director Chris Wray, telling him ‘your day is coming’",
    "guid": "b2456401",
    "categories": [
      "US politics",
      "Americas",
      "World"
    ],
    "isoDate": "2023-11-30T20:46:42.000Z"
  },
  {
    "creator": "Inga Parkel",
    "date": "2023-11-30T20:44:28+00:00",
    "title": "Squid Game: The Challenge contestants had to use lubricated condoms as chapstick",
    "link": "https://www.independent.co.uk/arts-entertainment/tv/news/squid-game-the-challenge-condoms-b2456426.html",
    "pubDate": "Thu, 30 Nov 2023 20:44:28 GMT",
    "dc:creator": "Inga Parkel",
    "dc:date": "2023-11-30T20:44:28+00:00",
    "content": "<p>Player 301 said that ‘within a day, maybe a day and a half, all the condoms were gone’ </p>",
    "contentSnippet": "Player 301 said that ‘within a day, maybe a day and a half, all the condoms were gone’",
    "guid": "b2456426",
    "categories": [
      "News",
      "TV &amp; Radio",
      "Culture"
    ],
    "isoDate": "2023-11-30T20:44:28.000Z"
  },
  {
    "creator": "Andy Sims",
    "date": "2023-11-30T20:43:53+00:00",
    "title": "David Moyes urges West Ham to finish the job and top Group A",
    "link": "https://www.independent.co.uk/sport/football/tomas-soucek-david-moyes-europa-league-west-ham-freiburg-b2456460.html",
    "pubDate": "Thu, 30 Nov 2023 20:43:53 GMT",
    "dc:creator": "Andy Sims",
    "dc:date": "2023-11-30T20:43:53+00:00",
    "content": "The Hammers need to avoid defeat to Freiburg at the London Stadium in a fortnight.",
    "contentSnippet": "The Hammers need to avoid defeat to Freiburg at the London Stadium in a fortnight.",
    "guid": "b2456460",
    "categories": [
      "Football",
      "Sport"
    ],
    "isoDate": "2023-11-30T20:43:53.000Z"
  },
  {
    "creator": "Katie Hawkinson",
    "date": "2023-11-30T20:38:41+00:00",
    "title": "Rand Paul performs Heimlich maneuver on Senator Joni Ernst during lunch ",
    "link": "https://www.the-independent.com/news/world/americas/us-politics/rand-paul-joni-ernst-heimlich-maneuver-senate-b2456431.html",
    "pubDate": "Thu, 30 Nov 2023 20:38:41 GMT",
    "dc:creator": "Katie Hawkinson",
    "dc:date": "2023-11-30T20:38:41+00:00",
    "content": "<p>‘Can’t help but choke on the woke policies Dems are forcing down our throats,’ Sen Joni Ernst writes after incident </p>",
    "contentSnippet": "‘Can’t help but choke on the woke policies Dems are forcing down our throats,’ Sen Joni Ernst writes after incident",
    "guid": "b2456431",
    "categories": [
      "US politics",
      "Americas",
      "World"
    ],
    "isoDate": "2023-11-30T20:38:41.000Z"
  },
  {
    "creator": "Gary Gerard Hamilton",
    "date": "2023-11-30T20:36:49+00:00",
    "title": "Eddie Murphy wants 'Candy Cane Lane' to put you in the Christmas spirit for years to come",
    "link": "https://www.independent.co.uk/news/eddie-murphy-ap-new-york-brooklyn-tracee-ellis-ross-b2456458.html",
    "pubDate": "Thu, 30 Nov 2023 20:36:49 GMT",
    "dc:creator": "Gary Gerard Hamilton",
    "dc:date": "2023-11-30T20:36:49+00:00",
    "content": "Eddie Murphy fondly remembers watching classic Christmas movies as a child with his family during the holidays",
    "contentSnippet": "Eddie Murphy fondly remembers watching classic Christmas movies as a child with his family during the holidays",
    "guid": "b2456458",
    "isoDate": "2023-11-30T20:36:49.000Z"
  },
  {
    "creator": "Simon Calder",
    "date": "2023-11-30T20:36:26+00:00",
    "title": "‘After 16 months, we’re in it for as long as it takes,’ says rail union boss as strikes resume",
    "link": "https://www.independent.co.uk/travel/news-and-advice/aslef-train-strike-rail-union-b2456007.html",
    "pubDate": "Thu, 30 Nov 2023 20:36:26 GMT",
    "dc:creator": "Simon Calder",
    "dc:date": "2023-11-30T20:36:26+00:00",
    "content": "<p>Mick Whelan, general secretary of Aslef, has called for another round of industrial action from the start of December</p>",
    "contentSnippet": "Mick Whelan, general secretary of Aslef, has called for another round of industrial action from the start of December",
    "guid": "b2456007",
    "categories": [
      "News &amp; Advice",
      "Travel"
    ],
    "isoDate": "2023-11-30T20:36:26.000Z"
  },
  {
    "creator": "Travis Loller",
    "date": "2023-11-30T20:35:22+00:00",
    "title": "Former ambassador and Republican politician sues to block Tennessee voting law",
    "link": "https://www.independent.co.uk/news/tennessee-ap-ambassador-republican-nashville-b2456457.html",
    "pubDate": "Thu, 30 Nov 2023 20:35:22 GMT",
    "dc:creator": "Travis Loller",
    "dc:date": "2023-11-30T20:35:22+00:00",
    "content": "Former Ambassador to Poland and longtime Republican politician Victor Ashe is suing Tennessee election officials over a state law he claims is so vague that he could be prosecuted for voting in a Republican primary",
    "contentSnippet": "Former Ambassador to Poland and longtime Republican politician Victor Ashe is suing Tennessee election officials over a state law he claims is so vague that he could be prosecuted for voting in a Republican primary",
    "guid": "b2456457",
    "isoDate": "2023-11-30T20:35:22.000Z"
  },
  {
    "creator": "Russ Bynum",
    "date": "2023-11-30T20:34:22+00:00",
    "title": "Georgia county seeking to dismiss lawsuit by slave descendants over rezoning of their island homes",
    "link": "https://www.independent.co.uk/news/georgia-ap-black-african-b2456455.html",
    "pubDate": "Thu, 30 Nov 2023 20:34:22 GMT",
    "dc:creator": "Russ Bynum",
    "dc:date": "2023-11-30T20:34:22+00:00",
    "content": "County commissioners in Georgia are asking a judge to throw out a lawsuit by Black residents descended from slaves who fear new zoning changes will force them to sell their island homes",
    "contentSnippet": "County commissioners in Georgia are asking a judge to throw out a lawsuit by Black residents descended from slaves who fear new zoning changes will force them to sell their island homes",
    "guid": "b2456455",
    "isoDate": "2023-11-30T20:34:22.000Z"
  },
  {
    "creator": "Amber Raiken",
    "date": "2023-11-30T20:27:12+00:00",
    "title": "Shannen Doherty reveals cancer has spread to her bones",
    "link": "https://www.independent.co.uk/life-style/shannen-doherty-breast-cancer-bones-b2456450.html",
    "pubDate": "Thu, 30 Nov 2023 20:27:12 GMT",
    "dc:creator": "Amber Raiken",
    "dc:date": "2023-11-30T20:27:12+00:00",
    "content": "<p>‘We are people who want to work and embrace life and keep moving forward,’ she says </p>",
    "contentSnippet": "‘We are people who want to work and embrace life and keep moving forward,’ she says",
    "guid": "b2456450",
    "categories": [
      "Lifestyle"
    ],
    "isoDate": "2023-11-30T20:27:12.000Z"
  },
  {
    "creator": "Rhys Jones",
    "date": "2023-11-30T20:27:07+00:00",
    "title": "Queen Victoria’s Christmas decorations set to be auctioned",
    "link": "https://www.independent.co.uk/tv/culture/queen-victoria-christmas-decorations-b2456452.html",
    "pubDate": "Thu, 30 Nov 2023 20:27:07 GMT",
    "dc:creator": "Rhys Jones",
    "dc:date": "2023-11-30T20:27:07+00:00",
    "content": "<p><a href=\"/topic/christmas\">Christmas</a> decorations belonging to Queen <a href=\"/topic/victoria\">Victoria</a> are set to be auctioned for £1,500 on 7 December.</p>",
    "contentSnippet": "Christmas decorations belonging to Queen Victoria are set to be auctioned for £1,500 on 7 December.",
    "guid": "b2456452",
    "categories": [
      "Culture",
      "Indy TV"
    ],
    "isoDate": "2023-11-30T20:27:07.000Z"
  },
  {
    "creator": "Leah Willingham",
    "date": "2023-11-30T20:21:42+00:00",
    "title": "Six West Virginia jail employees indicted in connection with death of incarcerated man",
    "link": "https://www.independent.co.uk/news/ap-west-virginia-charleston-jim-justice-corrections-b2456451.html",
    "pubDate": "Thu, 30 Nov 2023 20:21:42 GMT",
    "dc:creator": "Leah Willingham",
    "dc:date": "2023-11-30T20:21:42+00:00",
    "content": "Five former correctional officers in West Virginia have been indicted by a federal grand jury in connection with the 2022 death of a man at a regional jail",
    "contentSnippet": "Five former correctional officers in West Virginia have been indicted by a federal grand jury in connection with the 2022 death of a man at a regional jail",
    "guid": "b2456451",
    "isoDate": "2023-11-30T20:21:42.000Z"
  },
  {
    "creator": "Mike Bedigan",
    "date": "2023-11-30T20:18:39+00:00",
    "title": "Musk says antisemitic tweet was ‘foolish’ – but blames media for angry reaction",
    "link": "https://www.independent.co.uk/tech/elon-musk-antisemitic-tweet-x-b2456440.html",
    "pubDate": "Thu, 30 Nov 2023 20:18:39 GMT",
    "dc:creator": "Mike Bedigan",
    "dc:date": "2023-11-30T20:18:39+00:00",
    "content": "<p>The world’s richest man says he had ‘no problem being hated’ </p>",
    "contentSnippet": "The world’s richest man says he had ‘no problem being hated’",
    "guid": "b2456440",
    "categories": [
      "Tech"
    ],
    "isoDate": "2023-11-30T20:18:39.000Z"
  },
  {
    "creator": "Andrea Cavallier",
    "date": "2023-11-30T20:17:56+00:00",
    "title": "Gilgo Beach serial killer suspect’s wife officially linked to crime scene DNA, report says",
    "link": "https://www.the-independent.com/news/world/americas/crime/gilgo-beach-rex-heuermann-wife-dna-b2456316.html",
    "pubDate": "Thu, 30 Nov 2023 20:17:56 GMT",
    "dc:creator": "Andrea Cavallier",
    "dc:date": "2023-11-30T20:17:56+00:00",
    "content": "<p>Asa Ellerup’s hair was found on the burlap-wrapped bodies of three of the four women her husband is accused of killing </p>",
    "contentSnippet": "Asa Ellerup’s hair was found on the burlap-wrapped bodies of three of the four women her husband is accused of killing",
    "guid": "b2456316",
    "categories": [
      "US Crime News",
      "Americas",
      "World"
    ],
    "isoDate": "2023-11-30T20:17:56.000Z"
  },
  {
    "creator": "Isobel Lewis",
    "date": "2023-11-30T20:16:55+00:00",
    "title": "Kate dazzles at Royal Variety Performance as she puts on united front with William amid racism storm",
    "link": "https://www.independent.co.uk/life-style/royal-family/news/kate-william-royal-variety-show-endgame-b2456427.html",
    "pubDate": "Thu, 30 Nov 2023 20:16:55 GMT",
    "dc:creator": "Isobel Lewis",
    "dc:date": "2023-11-30T20:16:55+00:00",
    "content": "<p>Kate stunned in blue Toteme gown and glittering jewellery </p>",
    "contentSnippet": "Kate stunned in blue Toteme gown and glittering jewellery",
    "guid": "b2456427",
    "categories": [
      "Royal Family News",
      "Royal Family",
      "Lifestyle"
    ],
    "isoDate": "2023-11-30T20:16:55.000Z"
  },
  {
    "creator": "Rhys Jones",
    "date": "2023-11-30T20:15:13+00:00",
    "title": "John Kirby on death of Henry Kissinger: ‘He shaped foreign policy decisions for decades’",
    "link": "https://www.independent.co.uk/tv/news/henry-kissinger-death-john-kirby-b2456444.html",
    "pubDate": "Thu, 30 Nov 2023 20:15:13 GMT",
    "dc:creator": "Rhys Jones",
    "dc:date": "2023-11-30T20:15:13+00:00",
    "content": "<p><a href=\"/topic/white-house\">White House</a> spokesman <a href=\"/topic/john-kirby\">John Kirby</a> gave his condolences to the family of <a href=\"/topic/henry-kissinger\">Henry Kissinger</a> after his passing on Wednesday 29 November.</p>",
    "contentSnippet": "White House spokesman John Kirby gave his condolences to the family of Henry Kissinger after his passing on Wednesday 29 November.",
    "guid": "b2456444",
    "categories": [
      "News",
      "Indy TV"
    ],
    "isoDate": "2023-11-30T20:15:13.000Z"
  },
  {
    "creator": "Susan Montoya Bryan",
    "date": "2023-11-30T20:13:17+00:00",
    "title": "Work resumes on $10B renewable energy transmission project despite tribal objections",
    "link": "https://www.independent.co.uk/news/ap-bureau-of-land-management-work-new-mexico-biden-b2456446.html",
    "pubDate": "Thu, 30 Nov 2023 20:13:17 GMT",
    "dc:creator": "Susan Montoya Bryan",
    "dc:date": "2023-11-30T20:13:17+00:00",
    "content": "It's back to work for construction crews that are clearing land and building access roads for a $10 billion project that the Biden administration describes as an important part of the nation's transition to renewable energy",
    "contentSnippet": "It's back to work for construction crews that are clearing land and building access roads for a $10 billion project that the Biden administration describes as an important part of the nation's transition to renewable energy",
    "guid": "b2456446",
    "isoDate": "2023-11-30T20:13:17.000Z"
  },
  {
    "creator": "Andrea Blanco,Rachel Sharp and Sheila Flynn",
    "date": "2023-11-30T20:11:27+00:00",
    "title": "Four slain students, a weeks-long manhunt but no motive: What happened in the Idaho murders?",
    "link": "https://www.the-independent.com/news/world/americas/crime/idaho-murders-moscow-update-bryan-kohberger-b2456443.html",
    "pubDate": "Thu, 30 Nov 2023 20:11:27 GMT",
    "dc:creator": "Andrea Blanco,Rachel Sharp and Sheila Flynn",
    "dc:date": "2023-11-30T20:11:27+00:00",
    "content": "<p>As suspect Bryan Kohberger prepares to face trial, <strong>Andrea Blanco</strong>, <strong>Rachel Sharp</strong> and <strong>Sheila Flynn </strong>report on the case in small town Idaho that shocked America</p>",
    "contentSnippet": "As suspect Bryan Kohberger prepares to face trial, Andrea Blanco, Rachel Sharp and Sheila Flynn report on the case in small town Idaho that shocked America",
    "guid": "b2456443",
    "categories": [
      "US Crime News",
      "Americas",
      "World"
    ],
    "isoDate": "2023-11-30T20:11:27.000Z"
  },
  {
    "creator": "Kaleigh Werner",
    "date": "2023-11-30T20:09:53+00:00",
    "title": "Jennifer Lawrence addresses plastic surgery rumours",
    "link": "https://www.independent.co.uk/life-style/jennifer-lawrence-plastic-surgery-rumours-b2456442.html",
    "pubDate": "Thu, 30 Nov 2023 20:09:53 GMT",
    "dc:creator": "Kaleigh Werner",
    "dc:date": "2023-11-30T20:09:53+00:00",
    "content": "<p>‘Apparently, I’ve had full plastic surgery,’ Lawrence says </p>",
    "contentSnippet": "‘Apparently, I’ve had full plastic surgery,’ Lawrence says",
    "guid": "b2456442",
    "categories": [
      "Lifestyle"
    ],
    "isoDate": "2023-11-30T20:09:53.000Z"
  },
  {
    "creator": "Michelle L. Price",
    "date": "2023-11-30T20:09:39+00:00",
    "title": "RNC’s rules for 2024 convention don’t address what would happen if Trump is convicted",
    "link": "https://www.the-independent.com/news/world/americas/us-politics/republican-trump-rnc-convention-rules-b2456418.html",
    "pubDate": "Thu, 30 Nov 2023 20:09:39 GMT",
    "dc:creator": "Michelle L. Price",
    "dc:date": "2023-11-30T20:09:39+00:00",
    "content": "<p>Can delegates vote for a different candidate if the party’s presumptive nominee is convicted of a felony? </p>",
    "contentSnippet": "Can delegates vote for a different candidate if the party’s presumptive nominee is convicted of a felony?",
    "guid": "b2456418",
    "categories": [
      "US politics",
      "Americas",
      "World"
    ],
    "isoDate": "2023-11-30T20:09:39.000Z"
  },
  {
    "creator": "Olivia Hebert",
    "date": "2023-11-30T20:04:42+00:00",
    "title": "Steakhouse customer pays double for meal after miscommunication with waiter - who was in the right? ",
    "link": "https://www.independent.co.uk/life-style/tiktok-steakhouse-unlimited-sides-b2456441.html",
    "pubDate": "Thu, 30 Nov 2023 20:04:42 GMT",
    "dc:creator": "Olivia Hebert",
    "dc:date": "2023-11-30T20:04:42+00:00",
    "content": "<p>‘I just meant you could order as many as you wanted to,’ waiter tells customers </p>",
    "contentSnippet": "‘I just meant you could order as many as you wanted to,’ waiter tells customers",
    "guid": "b2456441",
    "categories": [
      "Lifestyle"
    ],
    "isoDate": "2023-11-30T20:04:42.000Z"
  },
  {
    "creator": "Meredith Clark",
    "date": "2023-11-30T20:02:31+00:00",
    "title": "Emily Ratajkowski’s latest photo shoot sparks fury",
    "link": "https://www.independent.co.uk/life-style/fashion/emily-ratajkowski-photo-shoot-plus-size-b2456439.html",
    "pubDate": "Thu, 30 Nov 2023 20:02:31 GMT",
    "dc:creator": "Meredith Clark",
    "dc:date": "2023-11-30T20:02:31+00:00",
    "content": "<p>Supermodel’s latest photo shoot has been accused by body inclusivity activists of being ‘fatphobic’  </p>",
    "contentSnippet": "Supermodel’s latest photo shoot has been accused by body inclusivity activists of being ‘fatphobic’",
    "guid": "b2456439",
    "categories": [
      "Fashion",
      "Lifestyle"
    ],
    "isoDate": "2023-11-30T20:02:31.000Z"
  },
  {
    "creator": "Brittany Miller",
    "date": "2023-11-30T20:01:27+00:00",
    "title": "Former royal chef explains unusual dinner rule for William and Kate’s children",
    "link": "https://www.independent.co.uk/life-style/royal-family/news/royal-family-chef-kate-william-kids-b2456437.html",
    "pubDate": "Thu, 30 Nov 2023 20:01:27 GMT",
    "dc:creator": "Brittany Miller",
    "dc:date": "2023-11-30T20:01:27+00:00",
    "content": "<p>Darren McGrady worked for royal family for 15 years </p>",
    "contentSnippet": "Darren McGrady worked for royal family for 15 years",
    "guid": "b2456437",
    "categories": [
      "Royal Family News",
      "Royal Family",
      "Lifestyle"
    ],
    "isoDate": "2023-11-30T20:01:27.000Z"
  },
  {
    "creator": "Ariana Baio",
    "date": "2023-11-30T19:54:50+00:00",
    "title": "Senate Judiciary authorises subpoenas of conservative activists in Supreme Court ethics probe",
    "link": "https://www.the-independent.com/news/world/americas/us-politics/supreme-court-ethics-subpoenas-crow-leo-b2456382.html",
    "pubDate": "Thu, 30 Nov 2023 19:54:50 GMT",
    "dc:creator": "Ariana Baio",
    "dc:date": "2023-11-30T19:54:50+00:00",
    "content": "<p>Thursday’s contentious hearing ended in an entirely Democratic vote after Republican members of the committee walked out </p>",
    "contentSnippet": "Thursday’s contentious hearing ended in an entirely Democratic vote after Republican members of the committee walked out",
    "guid": "b2456382",
    "categories": [
      "US politics",
      "Americas",
      "World"
    ],
    "isoDate": "2023-11-30T19:54:50.000Z"
  },
  {
    "creator": "Kevin E G Perry",
    "date": "2023-11-30T19:54:01+00:00",
    "title": "Zack Snyder says he doesn’t ‘get’ why people don’t like Amber Heard",
    "link": "https://www.independent.co.uk/arts-entertainment/films/news/amber-heard-zack-snyder-aquaman-b2456407.html",
    "pubDate": "Thu, 30 Nov 2023 19:54:01 GMT",
    "dc:creator": "Kevin E G Perry",
    "dc:date": "2023-11-30T19:54:01+00:00",
    "content": "<p>The ‘Justice League’ director said: ‘If other people don’t like her, I don’t know what to say.’ </p>",
    "contentSnippet": "The ‘Justice League’ director said: ‘If other people don’t like her, I don’t know what to say.’",
    "guid": "b2456407",
    "categories": [
      "News",
      "Film",
      "Culture"
    ],
    "isoDate": "2023-11-30T19:54:01.000Z"
  },
  {
    "creator": "Diane Jeantet and Mauricio Savarese",
    "date": "2023-11-30T19:53:58+00:00",
    "title": "Brazilian city enacts an ordinance secretly written by a surprising new staffer: ChatGPT",
    "link": "https://www.independent.co.uk/news/chatgpt-ap-city-harvard-law-school-openai-b2456432.html",
    "pubDate": "Thu, 30 Nov 2023 19:53:58 GMT",
    "dc:creator": "Diane Jeantet and Mauricio Savarese",
    "dc:date": "2023-11-30T19:53:58+00:00",
    "content": "City lawmakers in Brazil passed what appears to be the nation’s first legislation written entirely by artificial intelligence — after they were kept in the dark about its unprecedented origin",
    "contentSnippet": "City lawmakers in Brazil passed what appears to be the nation’s first legislation written entirely by artificial intelligence — after they were kept in the dark about its unprecedented origin",
    "guid": "b2456432",
    "isoDate": "2023-11-30T19:53:58.000Z"
  },
  {
    "creator": "Lisa Rathke",
    "date": "2023-11-30T19:51:52+00:00",
    "title": "Ex of man charged with shooting Palestinian students had police remove his gun from her home in 2013",
    "link": "https://www.independent.co.uk/news/ap-vermont-syracuse-palestinian-new-york-b2456433.html",
    "pubDate": "Thu, 30 Nov 2023 19:51:52 GMT",
    "dc:creator": "Lisa Rathke",
    "dc:date": "2023-11-30T19:51:52+00:00",
    "content": "Syracuse, New York, police say an ex-girlfriend of the man charged with recently shooting and wounding three college students of Palestinian descent in Vermont asked officers 10 years ago to remove his gun from her home",
    "contentSnippet": "Syracuse, New York, police say an ex-girlfriend of the man charged with recently shooting and wounding three college students of Palestinian descent in Vermont asked officers 10 years ago to remove his gun from her home",
    "guid": "b2456433",
    "isoDate": "2023-11-30T19:51:52.000Z"
  },
  {
    "creator": "Jake Coyle",
    "date": "2023-11-30T19:51:32+00:00",
    "title": "'Killers of the Flower Moon' named best film of 2023 by New York film critics",
    "link": "https://www.independent.co.uk/news/martin-scorsese-ap-new-york-tar-christopher-nolan-b2456436.html",
    "pubDate": "Thu, 30 Nov 2023 19:51:32 GMT",
    "dc:creator": "Jake Coyle",
    "dc:date": "2023-11-30T19:51:32+00:00",
    "content": "Martin Scorsese’s “Killers of the Flower Moon” has been named the best film of the year by the New York Film Critics Circle",
    "contentSnippet": "Martin Scorsese’s “Killers of the Flower Moon” has been named the best film of the year by the New York Film Critics Circle",
    "guid": "b2456436",
    "isoDate": "2023-11-30T19:51:32.000Z"
  },
  {
    "creator": "Via AP news wire",
    "date": "2023-11-30T19:50:48+00:00",
    "title": "Suspect in custody after 2 troopers fatally struck while aiding driver on Las Vegas freeway",
    "link": "https://www.independent.co.uk/news/las-vegas-ap-nevada-steve-wolfson-clark-county-b2456430.html",
    "pubDate": "Thu, 30 Nov 2023 19:50:48 GMT",
    "dc:creator": "Via AP news wire",
    "dc:date": "2023-11-30T19:50:48+00:00",
    "content": "Two Nevada state troopers have died after they were struck by a vehicle while helping another driver",
    "contentSnippet": "Two Nevada state troopers have died after they were struck by a vehicle while helping another driver",
    "guid": "b2456430",
    "isoDate": "2023-11-30T19:50:48.000Z"
  },
  {
    "creator": "Lindsay Whitehurst",
    "date": "2023-11-30T19:50:12+00:00",
    "title": "Police searching for two people accused in FBI agent carjacking in Washington",
    "link": "https://www.independent.co.uk/news/police-ap-fbi-joe-biden-metropolitan-police-department-b2456435.html",
    "pubDate": "Thu, 30 Nov 2023 19:50:12 GMT",
    "dc:creator": "Lindsay Whitehurst",
    "dc:date": "2023-11-30T19:50:12+00:00",
    "content": "Police are searching for two people after an FBI agent was carjacked in Washington D",
    "contentSnippet": "Police are searching for two people after an FBI agent was carjacked in Washington D",
    "guid": "b2456435",
    "isoDate": "2023-11-30T19:50:12.000Z"
  },
  {
    "creator": "Eric Garcia",
    "date": "2023-11-30T19:39:41+00:00",
    "title": "Voices: Newsom and DeSantis face off in the name of recognition and desperation",
    "link": "https://www.independent.co.uk/voices/newsom-desantis-debate-fox-news-b2456350.html",
    "pubDate": "Thu, 30 Nov 2023 19:39:41 GMT",
    "dc:creator": "Eric Garcia",
    "dc:date": "2023-11-30T19:39:41+00:00",
    "content": "<p>Their ‘debate’ on Fox News is an exercise in vanity that will do nothing to advance either of their ideas. But it will give them plenty of media attention</p>",
    "contentSnippet": "Their ‘debate’ on Fox News is an exercise in vanity that will do nothing to advance either of their ideas. But it will give them plenty of media attention",
    "guid": "b2456350",
    "categories": [
      "Voices"
    ],
    "isoDate": "2023-11-30T19:39:41.000Z"
  },
  {
    "creator": "Jerry Harmer",
    "date": "2023-11-30T19:39:21+00:00",
    "title": "Families reunite with 17 Thai hostages freed by Hamas at homecoming at Bangkok airport",
    "link": "https://www.independent.co.uk/news/ap-hamas-thai-israel-families-b2456198.html",
    "pubDate": "Thu, 30 Nov 2023 19:39:21 GMT",
    "dc:creator": "Jerry Harmer",
    "dc:date": "2023-11-30T19:39:21+00:00",
    "content": "Seventeen Thai workers released from captivity by the militant Hamas group have been greeted by family and friends, officials and journalists in an emotional homecoming at Bangkok’s international airport",
    "contentSnippet": "Seventeen Thai workers released from captivity by the militant Hamas group have been greeted by family and friends, officials and journalists in an emotional homecoming at Bangkok’s international airport",
    "guid": "b2456198",
    "isoDate": "2023-11-30T19:39:21.000Z"
  },
  {
    "creator": "Amelia Neath",
    "date": "2023-11-30T19:36:37+00:00",
    "title": "Wolverines may soon get government protection",
    "link": "https://www.independent.co.uk/news/world/americas/north-american-wolverine-protection-government-b2456366.html",
    "pubDate": "Thu, 30 Nov 2023 19:36:37 GMT",
    "dc:creator": "Amelia Neath",
    "dc:date": "2023-11-30T19:36:37+00:00",
    "content": "<p>There are around 300  wolverines left in the wild in the US, and could face extinction due to the melting of their habitat </p>",
    "contentSnippet": "There are around 300  wolverines left in the wild in the US, and could face extinction due to the melting of their habitat",
    "guid": "b2456366",
    "categories": [
      "Americas",
      "World"
    ],
    "isoDate": "2023-11-30T19:36:37.000Z"
  },
  {
    "creator": "Brittany Miller",
    "date": "2023-11-30T19:36:34+00:00",
    "title": "Woman defends throwing daughter ‘extravagant’ 5th birthday day after sister-in-law’s wedding",
    "link": "https://www.independent.co.uk/life-style/daughter-birthday-family-wedding-reddit-b2455817.html",
    "pubDate": "Thu, 30 Nov 2023 19:36:34 GMT",
    "dc:creator": "Brittany Miller",
    "dc:date": "2023-11-30T19:36:34+00:00",
    "content": "<p>‘I think it’s pretty crazy she’s getting jealous over a little girl but quite a few family members on her side are saying I’m in the wrong,’ she says </p>",
    "contentSnippet": "‘I think it’s pretty crazy she’s getting jealous over a little girl but quite a few family members on her side are saying I’m in the wrong,’ she says",
    "guid": "b2455817",
    "categories": [
      "Lifestyle"
    ],
    "isoDate": "2023-11-30T19:36:34.000Z"
  },
  {
    "creator": "Maira Butt",
    "date": "2023-11-30T19:34:20+00:00",
    "title": "Those stuck in Gaza spend the ceasefire checking if loved ones are alive: ‘We don’t think about the future’",
    "link": "https://www.independent.co.uk/news/world/middle-east/gaza-palestine-israel-bomb-idf-b2456244.html",
    "pubDate": "Thu, 30 Nov 2023 19:34:20 GMT",
    "dc:creator": "Maira Butt",
    "dc:date": "2023-11-30T19:34:20+00:00",
    "content": "<p>Palestinians in Gaza learn their loved ones have been found under the rubble as a ceasefire is extended for another day  </p>",
    "contentSnippet": "Palestinians in Gaza learn their loved ones have been found under the rubble as a ceasefire is extended for another day",
    "guid": "b2456244",
    "categories": [
      "Middle East",
      "World"
    ],
    "isoDate": "2023-11-30T19:34:20.000Z"
  },
  {
    "creator": "Isobel Lewis and Tom Murray",
    "date": "2023-11-30T17:23:54+00:00",
    "title": "I’m a Celebrity – live: Sam Thompson opens up about ADHD diagnosis as Josie Gibson quits trial",
    "link": "https://www.independent.co.uk/arts-entertainment/tv/news/im-a-celebrity-2023-latest-b2456338.html",
    "pubDate": "Thu, 30 Nov 2023 17:23:54 GMT",
    "dc:creator": "Isobel Lewis and Tom Murray",
    "dc:date": "2023-11-30T17:23:54+00:00",
    "content": "<p>Tensions are running high in camp </p>",
    "contentSnippet": "Tensions are running high in camp",
    "guid": "b2456338",
    "categories": [
      "News",
      "TV &amp; Radio",
      "Culture"
    ],
    "isoDate": "2023-11-30T17:23:54.000Z"
  },
  {
    "creator": "Carl Markham",
    "date": "2023-11-30T23:38:44+00:00",
    "title": "Jurgen Klopp satisfied as Liverpool secure top spot with a game to spare",
    "link": "https://www.independent.co.uk/sport/football/luis-diaz-jurgen-klopp-liverpool-europa-league-cody-gakpo-b2456524.html",
    "pubDate": "Thu, 30 Nov 2023 23:38:44 GMT",
    "dc:creator": "Carl Markham",
    "dc:date": "2023-11-30T23:38:44+00:00",
    "content": "Two goals from Cody Gakpo and one apiece from Luis Diaz and Mohamed Salah secured victory.",
    "contentSnippet": "Two goals from Cody Gakpo and one apiece from Luis Diaz and Mohamed Salah secured victory.",
    "guid": "b2456524",
    "categories": [
      "Football",
      "Sport"
    ],
    "isoDate": "2023-11-30T23:38:44.000Z"
  },
  {
    "creator": "Josh Funk",
    "date": "2023-11-30T23:33:29+00:00",
    "title": "Haslam family refutes allegation from Warren Buffett's company that it bribed truck stop chain execs",
    "link": "https://www.independent.co.uk/news/ap-warren-buffett-bill-haslam-omaha-berkshire-hathaway-b2456523.html",
    "pubDate": "Thu, 30 Nov 2023 23:33:29 GMT",
    "dc:creator": "Josh Funk",
    "dc:date": "2023-11-30T23:33:29+00:00",
    "content": "An attorney for the billionaire Haslam family has called the bribery allegations from Warren Buffett’s company a “wild invention.\"",
    "contentSnippet": "An attorney for the billionaire Haslam family has called the bribery allegations from Warren Buffett’s company a “wild invention.\"",
    "guid": "b2456523",
    "isoDate": "2023-11-30T23:33:29.000Z"
  }
]